probat/__init__.py
probat/__main__.py
probat/dict_conf.py
probat/probat.py
probat-1.1.0.dist-info/LICENSE
probat-1.1.0.dist-info/METADATA
probat-1.1.0.dist-info/WHEEL
probat-1.1.0.dist-info/entry_points.txt
probat-1.1.0.dist-info/top_level.txt
probat-1.1.0.dist-info/RECORD
