Metadata-Version: 2.1
Name: probat
Version: 1.1.0
Summary: Battery life saver and reminder
Home-page: https://github.com/codeswhite/probat
Author: Max G
Author-email: max3227@gmail.com
License: UNKNOWN
Platform: UNKNOWN
Classifier: Programming Language :: Python :: 3
Classifier: License :: OSI Approved :: MIT License
Classifier: Operating System :: Unix
Requires-Python: >=3.8
License-File: LICENSE
Requires-Dist: termcolor
